<?xml version="1.0" encoding="UTF-8"?>
<c c1="0">
    <d d1="10017" d2="北京"/>
    <d d1="10018" d2="重庆"/>
    <d d1="10019" d2="福州"/>
    <d d1="10020" d2="厦门"/>
    <d d1="10028" d2="广州"/>
    <d d1="10029" d2="韶关"/>
    <d d1="10030" d2="深圳"/>
    <d d1="10031" d2="珠海"/>
    <d d1="10032" d2="汕头"/>
    <d d1="10033" d2="佛山"/>
    <d d1="10034" d2="江门"/>
    <d d1="10035" d2="湛江"/>
    <d d1="10036" d2="茂名"/>
    <d d1="10037" d2="肇庆"/>
    <d d1="10038" d2="惠州"/>
    <d d1="10039" d2="梅州"/>
    <d d1="10040" d2="汕尾"/>
    <d d1="10041" d2="河源"/>
    <d d1="10042" d2="阳江"/>
    <d d1="10043" d2="清远"/>
    <d d1="10044" d2="东莞"/>
    <d d1="10045" d2="中山"/>
    <d d1="10046" d2="潮州"/>
    <d d1="10047" d2="揭阳"/>
    <d d1="10048" d2="云浮"/>
    <d d1="10049" d2="兰州"/>
    <d d1="10063" d2="南宁"/>
    <d d1="10077" d2="贵阳"/>
    <d d1="10086" d2="石家庄"/>
    <d d1="10097" d2="武汉"/>
    <d d1="10114" d2="哈尔滨"/>
    <d d1="10127" d2="海口"/>
    <d d1="10146" d2="郑州"/>
    <d d1="10164" d2="长沙"/>
    <d d1="10178" d2="长春"/>
    <d d1="10187" d2="南京"/>
    <d d1="10200" d2="南昌"/>
    <d d1="10211" d2="沈阳"/>
    <d d1="10225" d2="呼和浩特"/>
    <d d1="10237" d2="银川"/>
    <d d1="10242" d2="西宁"/>
    <d d1="10250" d2="成都"/>
    <d d1="10271" d2="济南"/>
    <d d1="10287" d2="上海"/>
    <d d1="10288" d2="太原"/>
    <d d1="10299" d2="西安"/>
    <d d1="10309" d2="天津"/>
    <d d1="10310" d2="乌鲁木齐"/>
    <d d1="10324" d2="拉萨"/>
    <d d1="10331" d2="昆明"/>
    <d d1="10347" d2="杭州"/>
    <d d1="10358" d2="台湾"/>
    <d d1="10359" d2="香港"/>
    <d d1="10360" d2="澳门"/>
</c>